NDIlib/NDIlib.cpython-37m-aarch64-linux-gnu.so
NDIlib/__init__.py
NDIlib/libndi.so
NDIlib/libndi.so.5
NDIlib/libndi.so.5.1.1
NDIlib/libndi_licenses.txt
ndi_python-5.1.1.4.dist-info/LICENSE
ndi_python-5.1.1.4.dist-info/METADATA
ndi_python-5.1.1.4.dist-info/WHEEL
ndi_python-5.1.1.4.dist-info/top_level.txt
ndi_python-5.1.1.4.dist-info/RECORD
